<?xml version="1.0" encoding="UTF-8" ?>
<!DOCTYPE mapper PUBLIC "-//mybatis.org//DTD Mapper 3.0//EN" "http://mybatis.org/dtd/mybatis-3-mapper.dtd" >
<mapper namespace="com.gome.threshold.dao.ThresholdHistoryMapper" >
  <resultMap id="BaseResultMap" type="com.gome.threshold.domain.ThresholdHistory" >
    <id column="id" property="id" jdbcType="BIGINT" />
    <result column="server_addr" property="serverAddr" jdbcType="VARCHAR" />
    <result column="db_name" property="dbName" jdbcType="VARCHAR" />
    <result column="tbs_name" property="tbsName" jdbcType="VARCHAR" />
    <result column="disk_group" property="diskGroup" jdbcType="VARCHAR" />
    <result column="db_port" property="dbPort" jdbcType="VARCHAR" />
    <result column="inst_name" property="instName" jdbcType="VARCHAR" />
    <result column="db_type" property="dbType" jdbcType="VARCHAR" />
    <result column="active" property="active" jdbcType="INTEGER" />
    <result column="total" property="total" jdbcType="INTEGER" />
    <result column="total_mb" property="totalMB" jdbcType="FLOAT" />
    <result column="used_mb" property="usedMB" jdbcType="FLOAT" />
    <result column="used_percent" property="usedPercent" jdbcType="FLOAT" />
    <result column="alarm_time" property="alarmTime" jdbcType="TIMESTAMP" />
    <result column="create_time" property="createTime" jdbcType="TIMESTAMP" />
    <result column="update_time" property="updateTime" jdbcType="TIMESTAMP" />
    <result column="pid" property="pid" jdbcType="BIGINT" />
  </resultMap>
  
  <sql id="Base_Column_List" >
    id, server_addr, db_name,
    tbs_name, disk_group, db_port, inst_name, db_type, active, total, total_mb, used_mb, used_percent, 
    alarm_time, create_time, update_time, pid
  </sql>
  
  <insert id="insertThresholdHistory" parameterType="com.gome.threshold.domain.ThresholdHistory" useGeneratedKeys="true" keyProperty="id">
    insert into gm_threshold_history (id, server_addr, db_name,
    tbs_name, disk_group, db_port, inst_name, db_type, active, total, total_mb, used_mb, used_percent,
    alarm_time, create_time, update_time, pid)
    values (#{id,jdbcType=BIGINT}, #{serverAddr,jdbcType=VARCHAR}, #{dbName,jdbcType=VARCHAR},
      #{tbsName,jdbcType=VARCHAR}, #{diskGroup,jdbcType=VARCHAR},
      #{dbPort,jdbcType=VARCHAR}, #{instName,jdbcType=VARCHAR},
      #{dbType,jdbcType=VARCHAR}, #{active,jdbcType=INTEGER},
      #{total,jdbcType=INTEGER}, #{totalMB,jdbcType=FLOAT},
      #{usedMB,jdbcType=FLOAT}, #{usedPercent,jdbcType=FLOAT},
      #{alarmTime,jdbcType=TIMESTAMP}, #{createTime,jdbcType=TIMESTAMP}, 
      #{updateTime,jdbcType=TIMESTAMP}, #{pid,jdbcType=BIGINT})
  </insert>
  <select id="selectThresholdHistoryListByPage" resultMap="BaseResultMap" parameterType="com.gome.threshold.common.Page">
  	select
  	<include refid="Base_Column_List"></include>
  	from gm_threshold_history
  	where 1=1 
 	<if test="conditions.id != null" >
      and id = #{conditions.id,jdbcType=BIGINT} 
    </if>
    <if test="conditions.serverAddr != null and conditions.serverAddr != ''" >
      and server_addr = #{conditions.serverAddr,jdbcType=VARCHAR}
    </if>
	<if test="conditions.dbName != null and conditions.dbName != ''" >
      and db_name = #{conditions.dbName,jdbcType=VARCHAR}  
    </if>
    <if test="conditions.tbsName != null and conditions.tbsName != ''" >
      and tbs_name = #{conditions.tbsName,jdbcType=VARCHAR} 
    </if>
    <if test="conditions.diskGroup != null and conditions.diskGroup != ''" >
      and disk_group = #{conditions.diskGroup,jdbcType=VARCHAR}
    </if>
    <if test="conditions.dbPort != null and conditions.dbPort != ''" >
      and db_port = #{conditions.dbPort,jdbcType=VARCHAR}
    </if>
    <if test="conditions.instName != null and conditions.instName != ''" >
      and inst_name = #{conditions.instName,jdbcType=VARCHAR}
    </if>
    <if test="conditions.dbType != null and conditions.dbType != ''" >
      and db_type = #{conditions.dbType,jdbcType=VARCHAR}
    </if>
    <if test="conditions.startTime != null and conditions.startTime != '' and conditions.endTime != null and conditions.endTime != ''" >
      and alarm_time between #{conditions.startTime} and #{conditions.endTime}
    </if>
    <if test="conditions.pid != null" >
      and pid = #{conditions.pid,jdbcType=BIGINT}
    </if>
    order by alarm_time desc
    <if test="start != null and pageSize != null">
    	LIMIT #{start},#{pageSize}
    </if>
  </select>
  <select id="selectTotalResultByConditions" resultType="java.lang.Integer" parameterType="com.gome.threshold.domain.ThresholdHistory">
  	select count(*) from gm_threshold_history
 	where 1=1 
 	<if test="id != null" >
      and id = #{id,jdbcType=BIGINT} 
    </if>
    <if test="serverAddr != null and serverAddr != ''" >
      and server_addr = #{serverAddr,jdbcType=VARCHAR}
    </if>
	<if test="dbName != null and dbName != ''" >
      and db_name = #{dbName,jdbcType=VARCHAR}  
    </if>
    <if test="tbsName != null and tbsName != ''" >
      and tbs_name = #{tbsName,jdbcType=VARCHAR} 
    </if>
    <if test="diskGroup != null and diskGroup != ''" >
      and disk_group = #{diskGroup,jdbcType=VARCHAR}
    </if>
    <if test="dbPort != null and dbPort != ''" >
      and db_port = #{dbPort,jdbcType=VARCHAR}
    </if>
    <if test="instName != null and instName != ''" >
      and inst_name = #{instName,jdbcType=VARCHAR}
    </if>
    <if test="dbType != null and dbType != ''" >
      and db_type = #{dbType,jdbcType=VARCHAR}
    </if>
    <if test="startTime != null and startTime != '' and endTime != null and endTime != ''" >
      and alarm_time between #{startTime} and #{endTime}
    </if>
    <if test="pid != null" >
      and pid = #{pid,jdbcType=BIGINT}
    </if>
  </select>
  <select id="selectThresholdHistoryById" parameterType="java.lang.Long" resultMap="BaseResultMap">
  	select 
  	<include refid="Base_Column_List"></include>
  	from gm_threshold_history 
 	where id = #{id} 
  </select>
  <select id="selectThresholdHistoryListByThresholdHistory" resultMap="BaseResultMap" parameterType="com.gome.threshold.domain.ThresholdHistory">
  	select 
  	<include refid="Base_Column_List"></include>  
    from gm_threshold_history 
  	where 1=1 
 	<if test="id != null" >
      and id = #{id,jdbcType=BIGINT} 
    </if>
    <if test="serverAddr != null and serverAddr != ''" >
      and server_addr = #{serverAddr,jdbcType=VARCHAR}
    </if>
	<if test="dbName != null and dbName != ''" >
      and db_name = #{dbName,jdbcType=VARCHAR}  
    </if>
    <if test="tbsName != null and tbsName != ''" >
      and tbs_name = #{tbsName,jdbcType=VARCHAR} 
    </if>
    <if test="diskGroup != null and diskGroup != ''" >
      and disk_group = #{diskGroup,jdbcType=VARCHAR}
    </if>
    <if test="dbPort != null and dbPort != ''" >
      and db_port = #{dbPort,jdbcType=VARCHAR}
    </if>
    <if test="instName != null and instName != ''" >
      and inst_name = #{instName,jdbcType=VARCHAR}
    </if>
    <if test="dbType != null and dbType != ''" >
      and db_type = #{dbType,jdbcType=VARCHAR}
    </if>
    <if test="startTime != null and startTime != '' and endTime != null and endTime != ''" >
      and alarm_time between #{startTime} and #{endTime}
    </if>
    <if test="pid != null" >
      and pid = #{pid,jdbcType=BIGINT}
    </if>
  </select>
  <update id="updateThresholdHistory" parameterType="com.gome.threshold.domain.ThresholdHistory" >
    update gm_threshold_history set
    <if test="id != null" >
      id = #{id,jdbcType=BIGINT} 
    </if>
    <if test="serverAddr != null" >
      , server_addr = #{serverAddr,jdbcType=VARCHAR}
    </if>
	<if test="dbName != null" >
      , db_name = #{dbName,jdbcType=VARCHAR}  
    </if>
    <if test="tbsName != null" >
      , tbs_name = #{tbsName,jdbcType=VARCHAR} 
    </if>
    <if test="diskGroup != null" >
      , disk_group = #{diskGroup,jdbcType=VARCHAR}
    </if>
    <if test="dbPort != null" >
      , db_port = #{dbPort,jdbcType=VARCHAR}
    </if>
    <if test="instName != null" >
      , inst_name = #{instName,jdbcType=VARCHAR}
    </if>
    <if test="dbType != null" >
      , db_type = #{dbType,jdbcType=VARCHAR}
    </if>
    <if test="active != null" >
      , active = #{active,jdbcType=INTEGER}
    </if>
    <if test="total != null" >
      , total = #{total,jdbcType=INTEGER}
    </if>
    <if test="totalMB != null" >
      , total_mb = #{totalMB,jdbcType=FLOAT}
    </if>
    <if test="usedMB != null" >
      , used_mb = #{usedMB,jdbcType=FLOAT}
    </if>
    <if test="usedPercent != null" >
      , used_percent = #{usedPercent,jdbcType=FLOAT}
    </if>
    <if test="alarmTime != null" >
      , alarm_time = #{alarmTime,jdbcType=TIMESTAMP}
    </if>
    <if test="createTime != null" >
      , create_time = #{createTime,jdbcType=TIMESTAMP}
    </if>
    <if test="updateTime != null" >
      , update_time = #{updateTime,jdbcType=TIMESTAMP}
    </if>
    <if test="pid != null" >
      , pid = #{pid,jdbcType=BIGINT}
    </if>
    where id = #{id,jdbcType=BIGINT}
  </update>
  <delete id="deleteThresholdHistoryById" parameterType="java.lang.Long" >
    delete from gm_threshold_history
    where id = #{id,jdbcType=BIGINT}
  </delete>
  <delete id="batchDeleteThresholdHistoryByIds" parameterType="java.lang.reflect.Array" >
    delete from gm_threshold_history
    where id in
    <foreach collection="array" index="index" item="item" open="(" separator="," close=")">  
            #{item} 
    </foreach>  
  </delete>
</mapper> 